sampling_tille/__init__.py
sampling_tille/data/HV_dem.csv
sampling_tille/data/aer_fertility.csv
sampling_tille/data/altitude.nc
sampling_tille/data/belgianmunicipalities.csv
sampling_tille/data/gdf_ny.geojson
sampling_tille/data/georef-italy-provincia-millesime.cpg
sampling_tille/data/georef-italy-provincia-millesime.dbf
sampling_tille/data/georef-italy-provincia-millesime.prj
sampling_tille/data/georef-italy-provincia-millesime.shp
sampling_tille/data/georef-italy-provincia-millesime.shx
sampling_tille/data/palmanova.geojson
sampling_tille/data/piedmont.nc
sampling_tille/data/piedmont.nc.aux.xml
sampling_tille/data/procida.geojson
sampling_tille/data/swissmunicipalities.csv
sampling_tille/df_sample.py
sampling_tille/grts.py
sampling_tille/load_data.py
sampling_tille/pivotal.py
sampling_tille/sample_points.py
sampling_tille/sampling.py
sampling_tille/stratify.py
sampling_tille/utils.py
sampling_tille/weights.py
sampling_tille-0.2.1.dist-info/LICENSE
sampling_tille-0.2.1.dist-info/METADATA
sampling_tille-0.2.1.dist-info/WHEEL
sampling_tille-0.2.1.dist-info/RECORD
