Metadata-Version: 2.3
Name: sampling_tille
Version: 0.2.1
Summary: Sampling routines ported from the sampling R package.
Author: Stippe
Requires-Python: >=3.12
Classifier: Programming Language :: Python :: 3
Classifier: Programming Language :: Python :: 3.12
Classifier: Programming Language :: Python :: 3.13
Requires-Dist: cvxpy (>=1.6.3,<2.0.0)
Requires-Dist: geopandas (>=1.0.1,<2.0.0)
Requires-Dist: jax (==0.5.0)
Requires-Dist: numpy (>=1.16,<3.0.0)
Requires-Dist: pandas (>=2.2.3,<3.0.0)
Requires-Dist: pyscipopt (>=5.4.1,<6.0.0)
Requires-Dist: rioxarray (==0.18.2)
Requires-Dist: scikit-learn (>=1.6.1,<2.0.0)
Requires-Dist: scipy (==1.15.2)
